causalchamber/__init__.py
causalchamber/utils.py
causalchamber/datasets/__init__.py
causalchamber/datasets/main.py
causalchamber/datasets/sampling.py
causalchamber/datasets/utils.py
causalchamber/ground_truth/__init__.py
causalchamber/ground_truth/main.py
causalchamber/lab/__init__.py
causalchamber/lab/api.py
causalchamber/lab/chamber.py
causalchamber/lab/exceptions.py
causalchamber/lab/lab.py
causalchamber/lab/test/__init__.py
causalchamber/lab/test/test_basic_flow.py
causalchamber/models/__init__.py
causalchamber/models/image_capture.py
causalchamber/models/light_tunnel_models.py
causalchamber/models/wind_tunnel_models.py
causalchamber/models/wind_tunnel_simulators.py
causalchamber/simulators/__init__.py
causalchamber/simulators/main.py
causalchamber/simulators/lt/__init__.py
causalchamber/simulators/lt/image/__init__.py
causalchamber/simulators/lt/image/decoder.py
causalchamber/simulators/lt/image/models_f.py
causalchamber/simulators/lt/sensors/__init__.py
causalchamber/simulators/lt/sensors/main.py
causalchamber/simulators/tutorials/test_scripts/tutorial_DecoderSimple.py
causalchamber/simulators/tutorials/test_scripts/tutorial_Deterministic.py
causalchamber/simulators/tutorials/test_scripts/tutorial_ModelsAB.py
causalchamber/simulators/tutorials/test_scripts/tutorial_ModelsF.py
causalchamber/simulators/wt/__init__.py
causalchamber/simulators/wt/main.py
causalchamber/test/__init__.py
causalchamber/test/test_downloads.py
causalchamber-0.2.3.dist-info/licenses/LICENSE.txt
causalchamber-0.2.3.dist-info/METADATA
causalchamber-0.2.3.dist-info/WHEEL
causalchamber-0.2.3.dist-info/top_level.txt
causalchamber-0.2.3.dist-info/RECORD
